<?xml version="1.0" encoding="utf-8" ?>
<dwsync>
<file name="amex.png" server="cuen.sgedu.site/www/" local="131183083092529106" remote="131153224800000000" Dst="0" />
<file name="amex.svg" server="cuen.sgedu.site/www/" local="131183101713939964" remote="131153224800000000" Dst="0" />
<file name="diners.png" server="cuen.sgedu.site/www/" local="131183083099996197" remote="131153224800000000" Dst="0" />
<file name="diners.svg" server="cuen.sgedu.site/www/" local="131183101702078719" remote="131153224800000000" Dst="0" />
<file name="discover.png" server="cuen.sgedu.site/www/" local="131183083109915600" remote="131153224800000000" Dst="0" />
<file name="discover.svg" server="cuen.sgedu.site/www/" local="131183101718494279" remote="131153224800000000" Dst="0" />
<file name="jcb.png" server="cuen.sgedu.site/www/" local="131183083112407969" remote="131153224800000000" Dst="0" />
<file name="jcb.svg" server="cuen.sgedu.site/www/" local="131183101706993371" remote="131153224800000000" Dst="0" />
<file name="laser.png" server="cuen.sgedu.site/www/" local="131183083119975141" remote="131153224800000000" Dst="0" />
<file name="laser.svg" server="cuen.sgedu.site/www/" local="131183101694721737" remote="131153224800000000" Dst="0" />
<file name="maestro.png" server="cuen.sgedu.site/www/" local="131183083129824482" remote="131153224800000000" Dst="0" />
<file name="maestro.svg" server="cuen.sgedu.site/www/" local="131183101709025298" remote="131153224800000000" Dst="0" />
<file name="mastercard.png" server="cuen.sgedu.site/www/" local="131183083134328795" remote="131153224800000000" Dst="0" />
<file name="mastercard.svg" server="cuen.sgedu.site/www/" local="131183101697134061" remote="131153224800000000" Dst="0" />
<file name="visa.png" server="cuen.sgedu.site/www/" local="131183083148662353" remote="131153224800000000" Dst="0" />
<file name="visa.svg" server="cuen.sgedu.site/www/" local="131183101690828062" remote="131153224800000000" Dst="0" />
</dwsync>