<?xml version="1.0" encoding="utf-8" ?>
<dwsync>
<file name="404.php" server="cuen.sgedu.site/www/" local="131183086629253397" remote="130631256000000000" Dst="0" />
<file name="archive.php" server="cuen.sgedu.site/www/" local="131183086633617564" remote="130626936000000000" Dst="0" />
<file name="author-bio.php" server="cuen.sgedu.site/www/" local="131183086639203019" remote="130631256000000000" Dst="0" />
<file name="comments.php" server="cuen.sgedu.site/www/" local="131183086643647216" remote="130631256000000000" Dst="0" />
<file name="content-link.php" server="cuen.sgedu.site/www/" local="131183086652275268" remote="130631256000000000" Dst="0" />
<file name="content-none.php" server="cuen.sgedu.site/www/" local="131183086657149855" remote="130631256000000000" Dst="0" />
<file name="content-page.php" server="cuen.sgedu.site/www/" local="131183086664606927" remote="130631256000000000" Dst="0" />
<file name="content-search.php" server="cuen.sgedu.site/www/" local="131183086669011100" remote="130631256000000000" Dst="0" />
<file name="content.php" server="cuen.sgedu.site/www/" local="131183086675977707" remote="130631256000000000" Dst="0" />
<file name="footer.php" server="cuen.sgedu.site/www/" local="131183086689470662" remote="131149076400000000" Dst="0" />
<file name="functions.php" server="cuen.sgedu.site/www/" local="131183086696997824" remote="131032225200000000" Dst="0" />
<file name="header.php" server="cuen.sgedu.site/www/" local="131183086742931252" remote="131020056000000000" Dst="0" />
<file name="image.php" server="cuen.sgedu.site/www/" local="131183086744803009" remote="130631256000000000" Dst="0" />
<file name="index.php" server="cuen.sgedu.site/www/" local="131183086768335300" remote="130626936000000000" Dst="0" />
<file name="page.php" server="cuen.sgedu.site/www/" local="131183086795070693" remote="130607928000000000" Dst="0" />
<file name="readme.txt" server="cuen.sgedu.site/www/" local="131183086802337553" remote="131045881200000000" Dst="0" />
<file name="rtl.css" server="cuen.sgedu.site/www/" local="131183086806901878" remote="130876632000000000" Dst="0" />
<file name="search.php" server="cuen.sgedu.site/www/" local="131183086813818478" remote="130631256000000000" Dst="0" />
<file name="sidebar.php" server="cuen.sgedu.site/www/" local="131183086818522899" remote="130607928000000000" Dst="0" />
<file name="single.php" server="cuen.sgedu.site/www/" local="131183086824228360" remote="130627800000000000" Dst="0" />
<file name="style.css" server="cuen.sgedu.site/www/" local="131183086843316531" remote="131045881200000000" Dst="0" />
<file name="screenshot.png" server="cuen.sgedu.site/www/" local="131183086875877299" remote="131027580600000000" Dst="0" />
</dwsync>